burntoolcli.py
burntool/__init__.py
burntool/burntool_lib.py
burntool/burntool_serial.py
burntool/burntool_timer.py
burntool/burntool_util.py
burntool/resources/patch.bin
burntool-0.1.6.dist-info/licenses/LICENSE
burntool-0.1.6.dist-info/METADATA
burntool-0.1.6.dist-info/WHEEL
burntool-0.1.6.dist-info/entry_points.txt
burntool-0.1.6.dist-info/top_level.txt
burntool-0.1.6.dist-info/RECORD
