Metadata-Version: 2.4
Name: burntool
Version: 0.1.6
Summary: Taolink TK8620 Burntool in python
Author-email: Cactes <contact@cactes.com>
Project-URL: Homepage, https://github.com/CactesTech/cactes-taolink-burntool
Project-URL: Bug Tracker, https://github.com/CactesTech/cactes-taolink-burntool/issues
Requires-Python: >=3.7
License-File: LICENSE
Requires-Dist: fire
Requires-Dist: intelhex
Requires-Dist: pyserial
Dynamic: license-file
